{"date":"2026-07-14","rankings":[{"ticker":"RRC","bucket":"core","sweet_spot":0.7311,"rank":1},{"ticker":"EXE","bucket":"core","sweet_spot":0.6812,"rank":2},{"ticker":"EQT","bucket":"core","sweet_spot":0.5255,"rank":3},{"ticker":"VST","bucket":"small/levered","sweet_spot":0.4571,"rank":4},{"ticker":"AR","bucket":"core","sweet_spot":0.3312,"rank":5},{"ticker":"LNG","bucket":"core","sweet_spot":0.1059,"rank":6},{"ticker":"CTRA","bucket":"core","sweet_spot":0.0,"rank":7},{"ticker":"AM","bucket":"core","sweet_spot":-0.0764,"rank":8},{"ticker":"OKE","bucket":"core","sweet_spot":-0.1516,"rank":9},{"ticker":"MPLX","bucket":"small/levered","sweet_spot":-0.2018,"rank":10},{"ticker":"ET","bucket":"core","sweet_spot":-0.2978,"rank":11},{"ticker":"KMI","bucket":"core","sweet_spot":-0.3345,"rank":12},{"ticker":"FLNG","bucket":"small/levered","sweet_spot":-0.3957,"rank":13},{"ticker":"VG","bucket":"core","sweet_spot":-0.4005,"rank":14},{"ticker":"WMB","bucket":"core","sweet_spot":-0.4456,"rank":15},{"ticker":"DTM","bucket":"small/levered","sweet_spot":-0.5283,"rank":16}]}